{
  "vendor": "Sentry",
  "vendor_id": "sentry",
  "product": "Sentry",
  "product_id": "sentry-sentry",
  "category": "web",
  "subcategory": "web-application",
  "versions": {},
  "all_versions": [
    {
      "name": "Sentry HTML Detection",
      "pattern": "<script[^>]*>\\s*Raven\\.config\\('[^']*', \\{\\s+release: '([0-9\\.]+)'",
      "version_group": 1,
      "priority": 100,
      "confidence": 0.7,
      "metadata": {
        "author": "Wappalyzer Import",
        "created_at": "2025-01-01",
        "updated_at": "2025-01-01",
        "description": "Detects Sentry from HTML content",
        "tags": [
          "wappalyzer",
          "html",
          "sentry"
        ],
        "source": "Wappalyzer",
        "license": "MIT"
      }
    },
    {
      "name": "Sentry HTML Detection",
      "pattern": "<script[^>]*src=\"[^\"]*browser\\.sentry\\-cdn\\.com/([0-9.]+)/bundle(?:\\.tracing)?(?:\\.min)?\\.js",
      "version_group": 1,
      "priority": 100,
      "confidence": 0.7,
      "metadata": {
        "author": "Wappalyzer Import",
        "created_at": "2025-01-01",
        "updated_at": "2025-01-01",
        "description": "Detects Sentry from HTML content",
        "tags": [
          "wappalyzer",
          "html",
          "sentry"
        ],
        "source": "Wappalyzer",
        "license": "MIT"
      }
    },
    {
      "name": "Sentry Script Detection",
      "pattern": "browser\\.sentry\\-cdn\\.com/([0-9.]+)/bundle(?:\\.tracing)?(?:\\.min)?\\.js",
      "version_group": 1,
      "priority": 130,
      "confidence": 0.7,
      "metadata": {
        "author": "Wappalyzer Import",
        "created_at": "2025-01-01",
        "updated_at": "2025-01-01",
        "description": "Detects Sentry from script tags",
        "tags": [
          "wappalyzer",
          "script",
          "sentry"
        ],
        "source": "Wappalyzer",
        "license": "MIT"
      }
    }
  ]
}