{
  "vendor": "Coppermine",
  "vendor_id": "coppermine",
  "product": "Coppermine",
  "product_id": "coppermine",
  "category": "web",
  "versions": {},
  "all_versions": [
    {
      "name": "Coppermine Pattern",
      "priority": 100,
      "confidence": 0.8,
      "metadata": {
        "author": "WhatWeb Project",
        "created_at": "2025-01-01",
        "updated_at": "2025-01-01",
        "description": "Pattern extracted from WhatWeb plugin for Coppermine",
        "tags": [
          "whatweb",
          "extracted"
        ],
        "test_cases": [
          {
            "input": "<title>Coppermine Photo Gallery - Home</title>",
            "expected_version": "unknown"
          }
        ]
      },
      "pattern": "<title>Coppermine\\ Photo\\ Gallery\\ \\-\\ Home</title>",
      "version_group": 0
    },
    {
      "name": "Coppermine Pattern",
      "priority": 100,
      "confidence": 0.8,
      "metadata": {
        "author": "WhatWeb Project",
        "created_at": "2025-01-01",
        "updated_at": "2025-01-01",
        "description": "Pattern extracted from WhatWeb plugin for Coppermine",
        "tags": [
          "whatweb",
          "extracted"
        ],
        "test_cases": [
          {
            "input": "Coppermine version: ([0-9.]+)[ n]*$Revision",
            "expected_version": "unknown"
          }
        ]
      },
      "pattern": "Coppermine version: ([0-9\\.]+)[ \\n]*\\$Revision",
      "version_group": 0
    },
    {
      "name": "Coppermine Pattern",
      "priority": 100,
      "confidence": 0.8,
      "metadata": {
        "author": "WhatWeb Project",
        "created_at": "2025-01-01",
        "updated_at": "2025-01-01",
        "description": "Pattern extracted from WhatWeb plugin for Coppermine",
        "tags": [
          "whatweb",
          "extracted"
        ],
        "test_cases": [
          {
            "input": "<!-- BEGIN album_list -->",
            "expected_version": "unknown"
          }
        ]
      },
      "pattern": "<!\\-\\-\\ BEGIN\\ album_list\\ \\-\\->",
      "version_group": 0
    },
    {
      "name": "powered by link",
      "priority": 100,
      "confidence": 0.8,
      "metadata": {
        "author": "WhatWeb Project",
        "created_at": "2025-01-01",
        "updated_at": "2025-01-01",
        "description": "Pattern extracted from WhatWeb plugin for Coppermine",
        "tags": [
          "whatweb",
          "extracted"
        ],
        "test_cases": [
          {
            "input": "Powered by <a href=\"http://(coppermine-gallery.net|coppermine.sf.net|coppermine.sourceforge.net)/\" [^>]+>Coppermine Photo Gallery</a>",
            "expected_version": "unknown"
          }
        ]
      },
      "pattern": "Powered by <a href=\"http://(coppermine-gallery.net|coppermine.sf.net|coppermine.sourceforge.net)/\" [^>]+>Coppermine Photo Gallery</a>",
      "version_group": 0
    },
    {
      "name": "Coppermine Pattern",
      "priority": 100,
      "confidence": 0.8,
      "metadata": {
        "author": "WhatWeb Project",
        "created_at": "2025-01-01",
        "updated_at": "2025-01-01",
        "description": "Pattern extracted from WhatWeb plugin for Coppermine",
        "tags": [
          "whatweb",
          "extracted"
        ],
        "test_cases": [
          {
            "input": "<!--Coppermine Photo Gallery ([d.]+)[^>]+-->",
            "expected_version": "unknown"
          }
        ]
      },
      "pattern": "<!--Coppermine Photo Gallery ([\\d\\.]+)[^>]+-->",
      "version_group": 0
    },
    {
      "name": "displayimage.php url",
      "priority": 50,
      "confidence": 0.5,
      "metadata": {
        "author": "WhatWeb Project",
        "created_at": "2025-01-01",
        "updated_at": "2025-01-01",
        "description": "Pattern extracted from WhatWeb plugin for Coppermine",
        "tags": [
          "whatweb",
          "extracted"
        ],
        "test_cases": [
          {
            "input": "<a href=\"[^\"]*/displayimage.php?album=[a-z0-9]+&pos=\">",
            "expected_version": "unknown"
          }
        ]
      },
      "pattern": "<a href=\"[^\"]*/displayimage.php\\?album=[a-z0-9]+&pos=\">",
      "version_group": 0
    }
  ],
  "subcategory": "web-application"
}