{
  "vendor": "Pro-Chat-Rooms",
  "vendor_id": "pro-chat-rooms",
  "product": "Pro-Chat-Rooms",
  "product_id": "pro-chat-rooms",
  "category": "web",
  "subcategory": "web-application",
  "versions": {},
  "all_versions": [
    {
      "name": "Pro-Chat-Rooms Pattern",
      "priority": 100,
      "confidence": 0.8,
      "metadata": {
        "author": "WhatWeb Project",
        "created_at": "2025-01-01",
        "updated_at": "2025-01-01",
        "description": "Pattern extracted from WhatWeb plugin for Pro-Chat-Rooms",
        "tags": [
          "whatweb",
          "extracted"
        ],
        "test_cases": [
          {
            "input": "<title>Pro Chat Rooms</title>",
            "expected_version": "unknown"
          }
        ],
        "compiled_pattern": true
      },
      "pattern": "<title>Pro\\ Chat\\ Rooms</title>",
      "version_group": 0
    },
    {
      "name": "Pro-Chat-Rooms Pattern",
      "priority": 100,
      "confidence": 0.8,
      "metadata": {
        "author": "WhatWeb Project",
        "created_at": "2025-01-01",
        "updated_at": "2025-01-01",
        "description": "Pattern extracted from WhatWeb plugin for Pro-Chat-Rooms",
        "tags": [
          "whatweb",
          "extracted"
        ],
        "test_cases": [
          {
            "input": "<tr id=\"doPasswordBox\"><td>Password:</td><td><input type=\"password\" name=\"password\" id=\"password\" value=\"\" onblur=\"def(\\",
            "expected_version": "unknown"
          }
        ],
        "compiled_pattern": true
      },
      "pattern": "<tr\\ id=\"doPasswordBox\"><td>Password:</td><td><input\\ type=\"password\"\\ name=\"password\"\\ id=\"password\"\\ value=\"\"\\ onblur=\"def\\(\\\\",
      "version_group": 0
    },
    {
      "name": "Pro-Chat-Rooms Pattern",
      "priority": 100,
      "confidence": 0.8,
      "metadata": {
        "author": "WhatWeb Project",
        "created_at": "2025-01-01",
        "updated_at": "2025-01-01",
        "description": "Pattern extracted from WhatWeb plugin for Pro-Chat-Rooms",
        "tags": [
          "whatweb",
          "extracted"
        ],
        "test_cases": [
          {
            "input": "\tshowError(\"char_error\", \"Sorry, Username is already registered.\");",
            "expected_version": "unknown"
          }
        ],
        "compiled_pattern": true
      },
      "pattern": "\\\tshowError\\(\"char_error\",\\ \"Sorry,\\ Username\\ is\\ already\\ registered\\.\"\\);",
      "version_group": 0
    }
  ]
}