{
  "vendor": "Adobe-Experience-Manager",
  "vendor_id": "adobe-experience-manager",
  "product": "Adobe-Experience-Manager",
  "product_id": "adobe-experience-manager",
  "category": "web",
  "versions": {},
  "all_versions": [
    {
      "name": "div class parbase",
      "priority": 100,
      "confidence": 0.8,
      "metadata": {
        "author": "WhatWeb Project",
        "created_at": "2025-01-01",
        "updated_at": "2025-01-01",
        "description": "Pattern extracted from WhatWeb plugin for Adobe-Experience-Manager",
        "tags": [
          "whatweb",
          "extracted"
        ]
      },
      "pattern": "<div class=\\\"[^\\\"]*parbase"
    },
    {
      "name": "div data-component-path jcr",
      "priority": 100,
      "confidence": 0.8,
      "metadata": {
        "author": "WhatWeb Project",
        "created_at": "2025-01-01",
        "updated_at": "2025-01-01",
        "description": "Pattern extracted from WhatWeb plugin for Adobe-Experience-Manager",
        "tags": [
          "whatweb",
          "extracted"
        ]
      },
      "pattern": "<div[^>]+data-component-path=\\\"[^\\\"+]jcr:"
    },
    {
      "name": "div class aem-Grid",
      "priority": 100,
      "confidence": 0.8,
      "metadata": {
        "author": "WhatWeb Project",
        "created_at": "2025-01-01",
        "updated_at": "2025-01-01",
        "description": "Pattern extracted from WhatWeb plugin for Adobe-Experience-Manager",
        "tags": [
          "whatweb",
          "extracted"
        ]
      },
      "pattern": "<div class=\\\"[^\\\"]*aem-Grid"
    },
    {
      "name": "/etc/designs/",
      "priority": 100,
      "confidence": 0.8,
      "metadata": {
        "author": "WhatWeb Project",
        "created_at": "2025-01-01",
        "updated_at": "2025-01-01",
        "description": "Pattern extracted from WhatWeb plugin for Adobe-Experience-Manager",
        "tags": [
          "whatweb",
          "extracted"
        ]
      },
      "pattern": "<script type=\"text/javascript\" src=\"/etc/designs/"
    },
    {
      "name": "/etc/clientlibs/",
      "priority": 100,
      "confidence": 0.8,
      "metadata": {
        "author": "WhatWeb Project",
        "created_at": "2025-01-01",
        "updated_at": "2025-01-01",
        "description": "Pattern extracted from WhatWeb plugin for Adobe-Experience-Manager",
        "tags": [
          "whatweb",
          "extracted"
        ]
      },
      "pattern": "<script type=\"text/javascript\" src=\"/etc/clientlibs/"
    },
    {
      "name": "/etc.clientlibs/",
      "priority": 100,
      "confidence": 0.8,
      "metadata": {
        "author": "WhatWeb Project",
        "created_at": "2025-01-01",
        "updated_at": "2025-01-01",
        "description": "Pattern extracted from WhatWeb plugin for Adobe-Experience-Manager",
        "tags": [
          "whatweb",
          "extracted"
        ]
      },
      "pattern": "<script type=\"text/javascript\" src=\"/etc\\.clientlibs/"
    }
  ]
}