{
  "vendor": "Apache-Flink",
  "vendor_id": "apache-flink",
  "product": "Apache-Flink",
  "product_id": "apache-flink",
  "category": "web",
  "subcategory": "web-application",
  "versions": {},
  "all_versions": [
    {
      "name": "Apache Flink in title",
      "priority": 100,
      "confidence": 0.8,
      "metadata": {
        "author": "WhatWeb Project",
        "created_at": "2025-01-01",
        "updated_at": "2025-01-01",
        "description": "Pattern extracted from WhatWeb plugin for Apache-Flink",
        "tags": [
          "whatweb",
          "extracted"
        ],
        "test_cases": [
          {
            "input": "<title>Apache Flink Web Dashboard</title>",
            "expected_version": "unknown"
          }
        ],
        "compiled_pattern": true
      },
      "pattern": "<title>Apache Flink Web Dashboard</title>",
      "version_group": 0
    }
  ]
}