{
  "vendor": "Velazquez",
  "vendor_id": "velazquez",
  "product": "Velazquez",
  "product_id": "velazquez",
  "category": "web",
  "versions": {},
  "all_versions": [
    {
      "name": "Velazquez Pattern",
      "priority": 100,
      "confidence": 0.8,
      "metadata": {
        "author": "WhatWeb Project",
        "created_at": "2025-01-01",
        "updated_at": "2025-01-01",
        "description": "Pattern extracted from WhatWeb plugin for Velazquez",
        "tags": [
          "whatweb",
          "extracted"
        ]
      },
      "pattern": "^Velazquez"
    },
    {
      "name": "Velazquez Pattern",
      "priority": 100,
      "confidence": 0.8,
      "metadata": {
        "author": "WhatWeb Project",
        "created_at": "2025-01-01",
        "updated_at": "2025-01-01",
        "description": "Pattern extracted from WhatWeb plugin for Velazquez",
        "tags": [
          "whatweb",
          "extracted"
        ],
        "test_cases": [
          {
            "input": "Server: ^Velazquez 8.5$",
            "expected_version": "8.5"
          }
        ]
      },
      "pattern": "Server: ^Velazquez ([\\d\\.]+)$",
      "version_group": 1
    }
  ]
}