{
  "vendor": "Request-Tracker",
  "vendor_id": "request-tracker",
  "product": "Request-Tracker",
  "product_id": "request-tracker",
  "category": "web",
  "versions": {},
  "all_versions": [
    {
      "name": "Request-Tracker Pattern",
      "priority": 100,
      "confidence": 0.8,
      "metadata": {
        "author": "WhatWeb Project",
        "created_at": "2025-01-01",
        "updated_at": "2025-01-01",
        "description": "Pattern extracted from WhatWeb plugin for Request-Tracker",
        "tags": [
          "whatweb",
          "extracted"
        ],
        "test_cases": [
          {
            "input": "<link rel=\"stylesheet\" href=\"/NoAuth/webrtfm.css\" type=\"text/css\" />",
            "expected_version": "unknown"
          }
        ]
      },
      "pattern": "<link\\ rel=\"stylesheet\"\\ href=\"/NoAuth/webrtfm\\.css\"\\ type=\"text/css\"\\ />",
      "version_group": 0
    },
    {
      "name": "Request-Tracker Pattern",
      "priority": 100,
      "confidence": 0.8,
      "metadata": {
        "author": "WhatWeb Project",
        "created_at": "2025-01-01",
        "updated_at": "2025-01-01",
        "description": "Pattern extracted from WhatWeb plugin for Request-Tracker",
        "tags": [
          "whatweb",
          "extracted"
        ],
        "test_cases": [
          {
            "input": "<link rel=\"stylesheet\" href=\"/RTIR/NoAuth/webrtir.css\" type=\"text/css\">",
            "expected_version": "unknown"
          }
        ]
      },
      "pattern": "<link\\ rel=\"stylesheet\"\\ href=\"/RTIR/NoAuth/webrtir\\.css\"\\ type=\"text/css\">",
      "version_group": 0
    },
    {
      "name": "Request-Tracker Pattern",
      "priority": 100,
      "confidence": 0.8,
      "metadata": {
        "author": "WhatWeb Project",
        "created_at": "2025-01-01",
        "updated_at": "2025-01-01",
        "description": "Pattern extracted from WhatWeb plugin for Request-Tracker",
        "tags": [
          "whatweb",
          "extracted"
        ],
        "test_cases": [
          {
            "input": "<link rel=\"shortcut icon\" href=\"/NoAuth/images//favicon.png\" type=\"image/png\" />",
            "expected_version": "unknown"
          }
        ]
      },
      "pattern": "<link\\ rel=\"shortcut\\ icon\"\\ href=\"/NoAuth/images//favicon\\.png\"\\ type=\"image/png\"\\ />",
      "version_group": 0
    },
    {
      "name": "Request-Tracker Pattern",
      "priority": 100,
      "confidence": 0.8,
      "metadata": {
        "author": "WhatWeb Project",
        "created_at": "2025-01-01",
        "updated_at": "2025-01-01",
        "description": "Pattern extracted from WhatWeb plugin for Request-Tracker",
        "tags": [
          "whatweb",
          "extracted"
        ],
        "test_cases": [
          {
            "input": "<link rel=\"shortcut icon\" href=\"/NoAuth/images/favicon.png\" type=\"image/png\" />",
            "expected_version": "unknown"
          }
        ]
      },
      "pattern": "<link\\ rel=\"shortcut\\ icon\"\\ href=\"/NoAuth/images/favicon\\.png\"\\ type=\"image/png\"\\ />",
      "version_group": 0
    },
    {
      "name": "Request-Tracker Pattern",
      "priority": 100,
      "confidence": 0.8,
      "metadata": {
        "author": "WhatWeb Project",
        "created_at": "2025-01-01",
        "updated_at": "2025-01-01",
        "description": "Pattern extracted from WhatWeb plugin for Request-Tracker",
        "tags": [
          "whatweb",
          "extracted"
        ],
        "test_cases": [
          {
            "input": "<link rel=\"stylesheet\" href=\"/NoAuth/css/print.css\" type=\"text/css\" media=\"print\" />",
            "expected_version": "unknown"
          }
        ]
      },
      "pattern": "<link\\ rel=\"stylesheet\"\\ href=\"/NoAuth/css/print\\.css\"\\ type=\"text/css\"\\ media=\"print\"\\ />",
      "version_group": 0
    },
    {
      "name": "Request-Tracker Pattern",
      "priority": 25,
      "confidence": 0.25,
      "metadata": {
        "author": "WhatWeb Project",
        "created_at": "2025-01-01",
        "updated_at": "2025-01-01",
        "description": "Pattern extracted from WhatWeb plugin for Request-Tracker",
        "tags": [
          "whatweb",
          "extracted"
        ],
        "test_cases": [
          {
            "input": "<p id=\"bpscredits\">",
            "expected_version": "unknown"
          }
        ]
      },
      "pattern": "<p\\ id=\"bpscredits\">",
      "version_group": 0
    },
    {
      "name": "Request-Tracker Pattern",
      "priority": 100,
      "confidence": 0.8,
      "metadata": {
        "author": "WhatWeb Project",
        "created_at": "2025-01-01",
        "updated_at": "2025-01-01",
        "description": "Pattern extracted from WhatWeb plugin for Request-Tracker",
        "tags": [
          "whatweb",
          "extracted"
        ],
        "test_cases": [
          {
            "input": "<span class=\"rtname\">RT for ([^<]+)</span>",
            "expected_version": "unknown"
          }
        ]
      },
      "pattern": "<span class=\"rtname\">RT for ([^<]+)</span>",
      "version_group": 0
    }
  ],
  "subcategory": "web-application"
}